{"A": ["3014.0", "386"], "B": ["3069.0", "364"], "C": ["3022.0", "363"], "D": ["3031.0", "345"], "E": ["3042.0", "342"], "F": ["3005.0", "318"], "G": ["3064.0", "315"], "H": ["3082.0", "278"], "I": ["3063.0", "241"], "J": ["3035.0", "234"], "K": ["3067.0", "224"], "L": ["3048.0", "210"], "M": ["3030.0", "204"], "N": ["3023.0", "201"], "O": ["3038.0", "194"], "P": ["3006.0", "188"], "Q": ["3062.0", "167"], "R": ["3032.0", "167"], "S": ["3074.0", "167"], "T": ["3019.0", "148"], "U": ["3075.0", "148"], "V": ["3076.0", "146"], "W": ["3055.0", "142"], "X": ["3047.0", "135"], "Y": ["3007.0", "135"], "Z": ["3034.0", "127"]}